siili_ai_sdk/__init__.py
siili_ai_sdk/py.typed
siili_ai_sdk/agent/__init__.py
siili_ai_sdk/agent/base_agent.py
siili_ai_sdk/attachments/__init__.py
siili_ai_sdk/attachments/builder.py
siili_ai_sdk/attachments/file_storage_provider.py
siili_ai_sdk/attachments/mime_types.py
siili_ai_sdk/attachments/models.py
siili_ai_sdk/attachments/provider_support.py
siili_ai_sdk/attachments/storage/__init__.py
siili_ai_sdk/attachments/storage/base_file_storage.py
siili_ai_sdk/attachments/storage/impl/__init__.py
siili_ai_sdk/attachments/storage/impl/local_file_storage.py
siili_ai_sdk/audio/__init__.py
siili_ai_sdk/audio/options.py
siili_ai_sdk/audio/stt.py
siili_ai_sdk/audio/tts.py
siili_ai_sdk/audio/providers/__init__.py
siili_ai_sdk/audio/providers/google_tts.py
siili_ai_sdk/audio/providers/openai_stt.py
siili_ai_sdk/audio/providers/openai_tts.py
siili_ai_sdk/config/credentials_provider.py
siili_ai_sdk/config/env.py
siili_ai_sdk/config/env_credentials_provider.py
siili_ai_sdk/config/get_credentials_provider.py
siili_ai_sdk/image_gen/__init__.py
siili_ai_sdk/image_gen/image_generator.py
siili_ai_sdk/image_gen/options.py
siili_ai_sdk/image_gen/providers/__init__.py
siili_ai_sdk/image_gen/providers/google.py
siili_ai_sdk/image_gen/providers/openai.py
siili_ai_sdk/llm/__init__.py
siili_ai_sdk/llm/cancellation_handle.py
siili_ai_sdk/llm/converters.py
siili_ai_sdk/llm/extract_error_message.py
siili_ai_sdk/llm/langchain_loop_manager.py
siili_ai_sdk/llm/langchain_service.py
siili_ai_sdk/llm/message_handler.py
siili_ai_sdk/llm/consumption/__init__.py
siili_ai_sdk/llm/consumption/consumption_estimate.py
siili_ai_sdk/llm/consumption/consumption_estimate_builder.py
siili_ai_sdk/llm/consumption/consumption_extractor.py
siili_ai_sdk/llm/consumption/token_usage.py
siili_ai_sdk/llm/cost/__init__.py
siili_ai_sdk/llm/cost/builtin_cost_provider.py
siili_ai_sdk/llm/cost/cost_estimate.py
siili_ai_sdk/llm/cost/cost_provider.py
siili_ai_sdk/llm/streaming/__init__.py
siili_ai_sdk-0.6.2.dist-info/METADATA
siili_ai_sdk-0.6.2.dist-info/WHEEL
siili_ai_sdk-0.6.2.dist-info/RECORD
